python_rabbitmq/__init__.py
python_rabbitmq/connection.py
python_rabbitmq/consumer.py
python_rabbitmq/producer.py
python_rabbitmq/refs.py
python_rabbitmq-0.1.1.dist-info/WHEEL
python_rabbitmq-0.1.1.dist-info/METADATA
python_rabbitmq-0.1.1.dist-info/RECORD
