Metadata-Version: 2.1
Name: python-rabbitmq
Version: 0.1.1
Summary: 
Author: Huynh Doan Thinh
Author-email: hdthinh@gmail.com
Requires-Python: >=3.10,<4.0
Classifier: Programming Language :: Python :: 3
Classifier: Programming Language :: Python :: 3.10
Requires-Dist: pika (>=1.3.0,<2.0.0)
